Metadata-Version: 1.1
Name: collides
Version: 0.0.4
Summary: A vehicle collision detector
Home-page: UNKNOWN
Author: Rashid Alyassi
Author-email: rashid.rs@hotmail.com
License: MIT
Keywords: collision
Platform: UNKNOWN
Classifier: Development Status :: 5 - Production/Stable
Classifier: Intended Audience :: Education
Classifier: Operating System :: Microsoft :: Windows :: Windows 10
Classifier: License :: OSI Approved :: MIT License
Classifier: Programming Language :: Python :: 3
